Metadata-Version: 2.1
Name: socketIO-client-MV
Version: 0.7.2
Summary: A socket.io client library
Home-page: https://github.com/MateLabs/socketIO-client
Author: Matelabs
Author-email: yb@matelabs.in
License: MIT
Platform: UNKNOWN
Classifier: Intended Audience :: Developers
Classifier: Programming Language :: Python
Classifier: License :: OSI Approved :: MIT License
Classifier: Development Status :: 5 - Production/Stable
Requires-Dist: requests (>=2.7.0)
Requires-Dist: six
Requires-Dist: websocket-client
